pyribbit/__init__.py
pyribbit/camera.py
pyribbit/constants.py
pyribbit/font.py
pyribbit/light.py
pyribbit/material.py
pyribbit/mesh.py
pyribbit/node.py
pyribbit/offscreen.py
pyribbit/primitive.py
pyribbit/renderer.py
pyribbit/sampler.py
pyribbit/scene.py
pyribbit/shader_program.py
pyribbit/texture.py
pyribbit/trackball.py
pyribbit/utils.py
pyribbit/version.py
pyribbit/viewer.py
pyribbit/fonts/OpenSans-Bold.ttf
pyribbit/fonts/OpenSans-BoldItalic.ttf
pyribbit/fonts/OpenSans-ExtraBold.ttf
pyribbit/fonts/OpenSans-ExtraBoldItalic.ttf
pyribbit/fonts/OpenSans-Italic.ttf
pyribbit/fonts/OpenSans-Light.ttf
pyribbit/fonts/OpenSans-LightItalic.ttf
pyribbit/fonts/OpenSans-Regular.ttf
pyribbit/fonts/OpenSans-Semibold.ttf
pyribbit/fonts/OpenSans-SemiboldItalic.ttf
pyribbit/platforms/__init__.py
pyribbit/platforms/base.py
pyribbit/platforms/egl.py
pyribbit/platforms/osmesa.py
pyribbit/platforms/pyglet_platform.py
pyribbit/shaders/debug_quad.frag
pyribbit/shaders/debug_quad.vert
pyribbit/shaders/flat.frag
pyribbit/shaders/flat.vert
pyribbit/shaders/mesh.frag
pyribbit/shaders/mesh.vert
pyribbit/shaders/mesh_depth.frag
pyribbit/shaders/mesh_depth.vert
pyribbit/shaders/segmentation.frag
pyribbit/shaders/segmentation.vert
pyribbit/shaders/text.frag
pyribbit/shaders/text.vert
pyribbit/shaders/vertex_normals.frag
pyribbit/shaders/vertex_normals.geom
pyribbit/shaders/vertex_normals.vert
pyribbit/shaders/vertex_normals_pc.geom
pyribbit-0.1.46.dist-info/LICENSE
pyribbit-0.1.46.dist-info/METADATA
pyribbit-0.1.46.dist-info/WHEEL
pyribbit-0.1.46.dist-info/top_level.txt
pyribbit-0.1.46.dist-info/RECORD
