Metadata-Version: 2.1
Name: pyribbit
Version: 0.1.46
Summary: Easy-to-use Python renderer for 3D visualization
Home-page: https://github.com/fishbotics/pyribbit
Author: Adam Fishman
Author-email: hello@fishbotics.com
License: MIT License
Keywords: rendering graphics opengl 3d visualization pbr gltf
Classifier: Development Status :: 4 - Beta
Classifier: License :: OSI Approved :: MIT License
Classifier: Operating System :: POSIX :: Linux
Classifier: Operating System :: MacOS :: MacOS X
Classifier: Programming Language :: Python :: 2.7
Classifier: Programming Language :: Python :: 3.5
Classifier: Programming Language :: Python :: 3.6
Classifier: Natural Language :: English
Classifier: Topic :: Scientific/Engineering
Provides-Extra: dev
Provides-Extra: docs
License-File: LICENSE
